sot_generator/__init__.py
sot_generator/cli.py
sot_generator-0.0.1.dist-info/METADATA
sot_generator-0.0.1.dist-info/WHEEL
sot_generator-0.0.1.dist-info/entry_points.txt
sot_generator-0.0.1.dist-info/RECORD
